octopus_proto/agent_server_pb2.py
octopus_proto/agent_server_pb2.pyi
octopus_proto/agent_server_pb2_grpc.py
octopus_proto/common_pb2.py
octopus_proto/common_pb2.pyi
octopus_proto/common_pb2_grpc.py
octopus_proto/kernel_server_pb2.py
octopus_proto/kernel_server_pb2.pyi
octopus_proto/kernel_server_pb2_grpc.py
octopus_proto-0.4.18.dist-info/METADATA
octopus_proto-0.4.18.dist-info/WHEEL
octopus_proto-0.4.18.dist-info/top_level.txt
octopus_proto-0.4.18.dist-info/RECORD
