Metadata-Version: 2.1
Name: octopus-proto
Version: 0.4.18
Summary: Open source code interpreter agent for LLM
Home-page: https://github.com/dbpunk-labs/octopus
Author: imotai
Author-email: wangtaize@dbpunk.com
Requires-Dist: grpc-google-iam-v1 >=0.12.6
Requires-Dist: grpcio-tools >=1.57.0
